CHANGES.txt
LICENSE.txt
MANIFEST.in
NOTICE.txt
README.md
setup.py
mortar/api/__init__.py
mortar/api/v2/__init__.py
mortar/api/v2/api.py
mortar/api/v2/cluster_configurations.py
mortar/api/v2/clusters.py
mortar/api/v2/gateways.py
mortar/api/v2/jobs.py
mortar/api/v2/projects.py
mortar/api/v2/schedules.py
mortar_api_python.egg-info/PKG-INFO
mortar_api_python.egg-info/SOURCES.txt
mortar_api_python.egg-info/dependency_links.txt
mortar_api_python.egg-info/namespace_packages.txt
mortar_api_python.egg-info/requires.txt
mortar_api_python.egg-info/top_level.txt
test/test_api.py
test/test_cluster_configurations.py
test/test_clusters.py
test/test_gateways.py
test/test_jobs.py
test/test_projects.py