Metadata-Version: 1.0
Name: mortar-api-python
Version: 0.3.20
Summary: Python API for Mortar
Home-page: http://github.com/mortardata/mortar-api-python
Author: Mortar Data
Author-email: info@mortardata.com
License: LICENSE.txt
Platform: UNKNOWN
